pybiotech/__init__.py
pybiotech/__init__.pyi
pybiotech/py.typed
pybiotech/classes/__init__.py
pybiotech/classes/__init__.pyi
pybiotech/classes/nih/__init__.py
pybiotech/classes/nih/__init__.pyi
pybiotech/classes/nih/https/__init__.py
pybiotech/classes/nih/https/__init__.pyi
pybiotech/classes/nih/https/pubchem/__init__.py
pybiotech/classes/nih/https/pubchem/__init__.pyi
pybiotech/classes/nih/https/pubchem/domain.cpython-311-x86_64-linux-gnu.so
pybiotech/classes/nih/https/pubchem/domain.pyi
pybiotech/classes/nih/https/pubchem/identify.cpython-311-x86_64-linux-gnu.so
pybiotech/classes/nih/https/pubchem/identify.pyi
pybiotech/classes/nih/https/pubchem/input_spec.cpython-311-x86_64-linux-gnu.so
pybiotech/classes/nih/https/pubchem/input_spec.pyi
pybiotech/classes/nih/https/pubchem/opera_spec.cpython-311-x86_64-linux-gnu.so
pybiotech/classes/nih/https/pubchem/opera_spec.pyi
pybiotech/classes/nih/https/pubchem/output_spec.cpython-311-x86_64-linux-gnu.so
pybiotech/classes/nih/https/pubchem/output_spec.pyi
pybiotech/classes/nih/https/pubchem/query_options.cpython-311-x86_64-linux-gnu.so
pybiotech/classes/nih/https/pubchem/query_options.pyi
pybiotech/classes/nih/https/pubchem/request.cpython-311-x86_64-linux-gnu.so
pybiotech/classes/nih/https/pubchem/request.pyi
pybiotech/classes/nih/https/pubchem/section/__init__.py
pybiotech/classes/nih/https/pubchem/section/domain.cpython-311-x86_64-linux-gnu.so
pybiotech/classes/nih/https/pubchem/section/domain.pyi
pybiotech/classes/nih/https/pubchem/section/namespace.cpython-311-x86_64-linux-gnu.so
pybiotech/classes/nih/https/pubchem/section/namespace.pyi
pybiotech/classes/nih/https/pubchem/section/nscompound.cpython-311-x86_64-linux-gnu.so
pybiotech/classes/nih/https/pubchem/section/nscompound.pyi
pybiotech/classes/uniprot/__init__.py
pybiotech/classes/uniprot/__init__.pyi
pybiotech/classes/uniprot/https/__init__.py
pybiotech/classes/uniprot/https/__init__.pyi
pybiotech-0.3.1.dist-info/METADATA
pybiotech-0.3.1.dist-info/WHEEL
pybiotech-0.3.1.dist-info/top_level.txt
pybiotech-0.3.1.dist-info/RECORD
